valverangequery/__init__.py
valverangequery/map_lib.py
valverangequery/player_lib.py
valverangequery/source_packet.py
valve_range_query_3-2.0.3.dist-info/LICENSE
valve_range_query_3-2.0.3.dist-info/METADATA
valve_range_query_3-2.0.3.dist-info/WHEEL
valve_range_query_3-2.0.3.dist-info/top_level.txt
valve_range_query_3-2.0.3.dist-info/RECORD
