Metadata-Version: 2.1
Name: valve-range-query-3
Version: 2.0.3
Summary: Python library for Query of Valve Servers over a range of IPs
Home-page: https://github.com/incontestableness/valve-range-query-3
Author: incontestableness
Author-email: whyistherumg0ne@protonmail.com
License: MIT
Keywords: valve query servers counter strike csgo team fortress tf2 left for dead l4d2
Platform: UNKNOWN
Classifier: Development Status :: 4 - Beta
Classifier: Intended Audience :: Developers
Classifier: Topic :: Software Development :: Build Tools
Classifier: License :: OSI Approved :: MIT License
Classifier: Programming Language :: Python :: 3.7
